hendria_distributions/Binomialdistribution.py
hendria_distributions/Gaussiandistribution.py
hendria_distributions/Generaldistribution.py
hendria_distributions/__init__.py
hendria_distributions-0.1.dist-info/DESCRIPTION.rst
hendria_distributions-0.1.dist-info/METADATA
hendria_distributions-0.1.dist-info/RECORD
hendria_distributions-0.1.dist-info/WHEEL
hendria_distributions-0.1.dist-info/metadata.json
hendria_distributions-0.1.dist-info/top_level.txt
